yt_music_down/__about__.py
yt_music_down/__init__.py
yt_music_down/main.py
yt_music_down-0.0.2.dist-info/METADATA
yt_music_down-0.0.2.dist-info/WHEEL
yt_music_down-0.0.2.dist-info/entry_points.txt
yt_music_down-0.0.2.dist-info/licenses/LICENSE.txt
yt_music_down-0.0.2.dist-info/RECORD
