Metadata-Version: 2.3
Name: yt-music-down
Version: 0.0.2
Summary: A tool to download music playlists from youtube
Project-URL: Documentation, https://github.com/vidyasagar0405/yt-music-down#readme
Project-URL: Issues, https://github.com/vidyasagar0405/yt-music-down/issues
Project-URL: Source, https://github.com/vidyasagar0405/yt-music-down
Author-email: vidyasagar0405 <vidyasagar0405@gmail.com>
License-Expression: MIT
License-File: LICENSE.txt
Classifier: Development Status :: 4 - Beta
Classifier: Programming Language :: Python
Classifier: Programming Language :: Python :: 3.8
Classifier: Programming Language :: Python :: 3.9
Classifier: Programming Language :: Python :: 3.10
Classifier: Programming Language :: Python :: 3.11
Classifier: Programming Language :: Python :: 3.12
Classifier: Programming Language :: Python :: Implementation :: CPython
Classifier: Programming Language :: Python :: Implementation :: PyPy
Requires-Python: >=3.8
Requires-Dist: pytubefix
Requires-Dist: rich
